fastembed_vectorstore-0.3.1.dist-info/METADATA
fastembed_vectorstore-0.3.1.dist-info/WHEEL
fastembed_vectorstore-0.3.1.dist-info/licenses/LICENSE
fastembed_vectorstore.pyi
fastembed_vectorstore/__init__.py
fastembed_vectorstore/__init__.pyi
fastembed_vectorstore/fastembed_vectorstore.cpython-312-darwin.so
fastembed_vectorstore/py.typed
fastembed_vectorstore-0.3.1.dist-info/RECORD
