Metadata-Version: 2.4
Name: fastembed_vectorstore
Version: 0.3.1
Classifier: Programming Language :: Rust
Classifier: Programming Language :: Python :: Implementation :: CPython
Classifier: Programming Language :: Python :: Implementation :: PyPy
License-File: LICENSE
Summary: A Rust-based in-memory vector store with fastembed
Keywords: fastembed,vectorstore,python,rust
Author-email: sauravniraula <developmentsaurav@gmail.com>
License-Expression: Apache-2.0
Requires-Python: >=3.8
Project-URL: Repository, https://github.com/sauravniraula/fastembed_vectorstore
Project-URL: Issues, https://github.com/sauravniraula/fastembed_vectorstore/issues
